README.txt
requirements.txt
setup.py
src/slacken/__init__.py
src/slacken/dicttypes.py
src/slacken/rest_access.py
src/slacken/version.txt
src/slacken/xml_accessor.py
src/slacken.egg-info/PKG-INFO
src/slacken.egg-info/SOURCES.txt
src/slacken.egg-info/dependency_links.txt
src/slacken.egg-info/requires.txt
src/slacken.egg-info/top_level.txt