Metadata-Version: 1.0
Name: slacken
Version: 0.1.4
Summary: Tools for working with rest
Home-page: https://github.com/alistair-broomhead/slacken
Author: Alistair Broomhead
Author-email: alistair.broomhead@gmail.com
License: MIT
Download-URL: https://github.com/alistair-broomhead/slacken/zipball/master
Platform: UNKNOWN
